LICENSE
MANIFEST.in
README.md
requirements.txt
setup.py
django_favicon_plus.egg-info/PKG-INFO
django_favicon_plus.egg-info/SOURCES.txt
django_favicon_plus.egg-info/dependency_links.txt
django_favicon_plus.egg-info/not-zip-safe
django_favicon_plus.egg-info/requires.txt
django_favicon_plus.egg-info/top_level.txt
favicon/__init__.py
favicon/admin.py
favicon/models.py
favicon/migrations/0001_initial.py
favicon/migrations/__init__.py
favicon/templatetags/__init__.py
favicon/templatetags/favtags.py